README
mcommand.py
setup.py
mcommand.egg-info/PKG-INFO
mcommand.egg-info/SOURCES.txt
mcommand.egg-info/dependency_links.txt
mcommand.egg-info/top_level.txt