Metadata-Version: 1.0
Name: mcommand
Version: 0.2.1
Summary: Mercurial-like command dispatch
Home-page: https://bitbucket.org/nytmyn/mcommand
Author: Jakub Dvorak
Author-email: nytmyn@gmail.com
License: BSD
Keywords: command console
Platform: UNKNOWN
Classifier: Development Status :: 3 - Alpha
Classifier: Environment :: Console
Classifier: Intended Audience :: Developers
Classifier: Intended Audience :: System Administrators
Classifier: License :: OSI Approved :: BSD License
Classifier: Natural Language :: English
Classifier: Operating System :: OS Independent
Classifier: Programming Language :: Python :: 2
Classifier: Topic :: Software Development
Classifier: Topic :: Software Development :: Libraries :: Python Modules
Classifier: Topic :: Software Development :: User Interfaces
Classifier: Topic :: Utilities
